photonx/__init__.py
photonx/index.py
photonx-0.0.4.dist-info/METADATA
photonx-0.0.4.dist-info/WHEEL
photonx-0.0.4.dist-info/licenses/LICENSE
photonx-0.0.4.dist-info/RECORD
