Metadata-Version: 2.3
Name: photonx
Version: 0.0.4
Summary: Collection of scripts useful for photonic design.
Project-URL: Homepage, https://github.com/NeuroSumbaD/photonx
Author-email: Luis El Srouji <lzelsrouji@ucdavis.edu>
License-File: LICENSE
Classifier: License :: OSI Approved :: MIT License
Classifier: Operating System :: OS Independent
Classifier: Programming Language :: Python :: 3
Requires-Python: >=3.8
